CallingGPT/__init__.py
CallingGPT/cli/__init__.py
CallingGPT/entities/__init__.py
CallingGPT/entities/namespace.py
CallingGPT/session/__init__.py
CallingGPT/session/session.py
CallingGPT-0.0.1.0.dist-info/METADATA
CallingGPT-0.0.1.0.dist-info/WHEEL
CallingGPT-0.0.1.0.dist-info/top_level.txt
CallingGPT-0.0.1.0.dist-info/RECORD
