Metadata-Version: 2.1
Name: CallingGPT
Version: 0.0.1.0
Summary: GPT's function calling feature wrapper
Home-page: https://github.com/RockChinQ/CallingGPT
Author: RockChinQ
Author-email: 1010553892@qq.com
Classifier: Programming Language :: Python :: 3
Classifier: License :: OSI Approved :: Apache Software License
Classifier: Operating System :: OS Independent
Requires-Dist: openai
